{
    "msg_travel": {
        "type": "hist",
        "pool": {
            "name": "msg_travel",
            "description": "Time taken (secs) to get here (receiver)",
            "marks": [
                0.0001,
                0.0005,
                0.001,
                0.002,
                0.004,
                0.008,
                0.01,
                0.02,
                0.04,
                0.08,
                0.1,
                0.2,
                0.4,
                0.8,
                1.0,
                2.0
            ],
            "unit": "second",
            "cat_data": {
                "site-1#req:task:register": [
                    {
                        "count": 1,
                        "total": 7.677078247070312e-05,
                        "min": 7.677078247070312e-05,
                        "max": 7.677078247070312e-05
                    },
                    "",
                    "",
                    "",
                    "",
                    "",
                    "",
                    "",
                    "",
                    "",
                    "",
                    "",
                    "",
                    "",
                    "",
                    "",
                    ""
                ],
                "site-2#req:task:register": [
                    {
                        "count": 1,
                        "total": 5.221366882324219e-05,
                        "min": 5.221366882324219e-05,
                        "max": 5.221366882324219e-05
                    },
                    "",
                    "",
                    "",
                    "",
                    "",
                    "",
                    "",
                    "",
                    "",
                    "",
                    "",
                    "",
                    "",
                    "",
                    "",
                    ""
                ],
                "site-2.simulate_job#req:server_parent_listener:get_clients": [
                    "",
                    "",
                    "",
                    "",
                    "",
                    "",
                    "",
                    "",
                    {
                        "count": 1,
                        "total": 0.021908044815063477,
                        "min": 0.021908044815063477,
                        "max": 0.021908044815063477
                    },
                    "",
                    "",
                    "",
                    "",
                    "",
                    "",
                    "",
                    ""
                ],
                "site-1.simulate_job#req:server_parent_listener:get_clients": [
                    "",
                    "",
                    "",
                    "",
                    "",
                    "",
                    "",
                    "",
                    {
                        "count": 1,
                        "total": 0.026245594024658203,
                        "min": 0.026245594024658203,
                        "max": 0.026245594024658203
                    },
                    "",
                    "",
                    "",
                    "",
                    "",
                    "",
                    "",
                    ""
                ],
                "site-2.simulate_job#fwd.req:sm__STREAM:sm__DATA": [
                    "",
                    {
                        "count": 4,
                        "total": 0.0011515617370605469,
                        "min": 0.00023746490478515625,
                        "max": 0.0003352165222167969
                    },
                    {
                        "count": 3,
                        "total": 0.002041339874267578,
                        "min": 0.0005364418029785156,
                        "max": 0.0009648799896240234
                    },
                    {
                        "count": 1,
                        "total": 0.0010683536529541016,
                        "min": 0.0010683536529541016,
                        "max": 0.0010683536529541016
                    },
                    "",
                    "",
                    "",
                    "",
                    "",
                    "",
                    "",
                    "",
                    "",
                    "",
                    "",
                    "",
                    ""
                ],
                "server.simulate_job#fwd.req:sm__STREAM:sm__DATA": [
                    {
                        "count": 26,
                        "total": 0.0007700920104980469,
                        "min": 1.71661376953125e-05,
                        "max": 9.751319885253906e-05
                    },
                    {
                        "count": 2,
                        "total": 0.00023317337036132812,
                        "min": 0.0001049041748046875,
                        "max": 0.00012826919555664062
                    },
                    "",
                    "",
                    "",
                    "",
                    "",
                    "",
                    "",
                    "",
                    "",
                    "",
                    "",
                    "",
                    "",
                    "",
                    ""
                ],
                "site-1.simulate_job#fwd.req:sm__STREAM:sm__DATA": [
                    "",
                    {
                        "count": 16,
                        "total": 0.005360841751098633,
                        "min": 0.0001888275146484375,
                        "max": 0.00043129920959472656
                    },
                    "",
                    {
                        "count": 3,
                        "total": 0.003437519073486328,
                        "min": 0.0010178089141845703,
                        "max": 0.001390695571899414
                    },
                    {
                        "count": 1,
                        "total": 0.002560853958129883,
                        "min": 0.002560853958129883,
                        "max": 0.002560853958129883
                    },
                    "",
                    "",
                    "",
                    "",
                    "",
                    "",
                    "",
                    "",
                    "",
                    "",
                    "",
                    ""
                ],
                "site-1.simulate_job#req:cellnet.channel:bye": [
                    "",
                    "",
                    {
                        "count": 1,
                        "total": 0.0006380081176757812,
                        "min": 0.0006380081176757812,
                        "max": 0.0006380081176757812
                    },
                    "",
                    "",
                    "",
                    "",
                    "",
                    "",
                    "",
                    "",
                    "",
                    "",
                    "",
                    "",
                    "",
                    ""
                ],
                "site-2.simulate_job#req:cellnet.channel:bye": [
                    "",
                    "",
                    "",
                    "",
                    {
                        "count": 1,
                        "total": 0.0037109851837158203,
                        "min": 0.0037109851837158203,
                        "max": 0.0037109851837158203
                    },
                    "",
                    "",
                    "",
                    "",
                    "",
                    "",
                    "",
                    "",
                    "",
                    "",
                    "",
                    ""
                ]
            }
        }
    },
    "msg_travel@server.simulate_job": {
        "type": "hist",
        "pool": {
            "name": "msg_travel@server.simulate_job",
            "description": "Time taken (secs) to get here (receiver)",
            "marks": [
                0.0001,
                0.0005,
                0.001,
                0.002,
                0.004,
                0.008,
                0.01,
                0.02,
                0.04,
                0.08,
                0.1,
                0.2,
                0.4,
                0.8,
                1.0,
                2.0
            ],
            "unit": "second",
            "cat_data": {
                "site-2.simulate_job#req:sm__STREAM:sm__DATA": [
                    "",
                    {
                        "count": 4,
                        "total": 0.0015773773193359375,
                        "min": 0.0003228187561035156,
                        "max": 0.0004639625549316406
                    },
                    {
                        "count": 2,
                        "total": 0.0016024112701416016,
                        "min": 0.0007758140563964844,
                        "max": 0.0008265972137451172
                    },
                    {
                        "count": 2,
                        "total": 0.003014802932739258,
                        "min": 0.0014543533325195312,
                        "max": 0.0015604496002197266
                    },
                    "",
                    "",
                    "",
                    "",
                    "",
                    "",
                    "",
                    "",
                    "",
                    "",
                    "",
                    "",
                    ""
                ],
                "site-1.simulate_job#req:sm__STREAM:sm__DATA": [
                    "",
                    {
                        "count": 13,
                        "total": 0.0056383609771728516,
                        "min": 0.000274658203125,
                        "max": 0.0004944801330566406
                    },
                    {
                        "count": 3,
                        "total": 0.0016858577728271484,
                        "min": 0.0005028247833251953,
                        "max": 0.0006537437438964844
                    },
                    {
                        "count": 2,
                        "total": 0.003081798553466797,
                        "min": 0.0015325546264648438,
                        "max": 0.0015492439270019531
                    },
                    {
                        "count": 1,
                        "total": 0.002811431884765625,
                        "min": 0.002811431884765625,
                        "max": 0.002811431884765625
                    },
                    {
                        "count": 1,
                        "total": 0.00506281852722168,
                        "min": 0.00506281852722168,
                        "max": 0.00506281852722168
                    },
                    "",
                    "",
                    "",
                    "",
                    "",
                    "",
                    "",
                    "",
                    "",
                    "",
                    ""
                ]
            }
        }
    },
    "msg_travel@site-1": {
        "type": "hist",
        "pool": {
            "name": "msg_travel@site-1",
            "description": "Time taken (secs) to get here (receiver)",
            "marks": [
                0.0001,
                0.0005,
                0.001,
                0.002,
                0.004,
                0.008,
                0.01,
                0.02,
                0.04,
                0.08,
                0.1,
                0.2,
                0.4,
                0.8,
                1.0,
                2.0
            ],
            "unit": "second",
            "cat_data": {
                "server#reply:task:register": [
                    {
                        "count": 1,
                        "total": 2.8133392333984375e-05,
                        "min": 2.8133392333984375e-05,
                        "max": 2.8133392333984375e-05
                    },
                    "",
                    "",
                    "",
                    "",
                    "",
                    "",
                    "",
                    "",
                    "",
                    "",
                    "",
                    "",
                    "",
                    "",
                    "",
                    ""
                ]
            }
        }
    },
    "msg_travel@site-2": {
        "type": "hist",
        "pool": {
            "name": "msg_travel@site-2",
            "description": "Time taken (secs) to get here (receiver)",
            "marks": [
                0.0001,
                0.0005,
                0.001,
                0.002,
                0.004,
                0.008,
                0.01,
                0.02,
                0.04,
                0.08,
                0.1,
                0.2,
                0.4,
                0.8,
                1.0,
                2.0
            ],
            "unit": "second",
            "cat_data": {
                "server#reply:task:register": [
                    {
                        "count": 1,
                        "total": 2.6702880859375e-05,
                        "min": 2.6702880859375e-05,
                        "max": 2.6702880859375e-05
                    },
                    "",
                    "",
                    "",
                    "",
                    "",
                    "",
                    "",
                    "",
                    "",
                    "",
                    "",
                    "",
                    "",
                    "",
                    "",
                    ""
                ]
            }
        }
    },
    "received_msg_counters": {
        "type": "counter",
        "pool": {
            "name": "received_msg_counters",
            "description": "Result counters of received messages",
            "counter_names": [
                "received",
                "replied",
                "ok",
                "forward"
            ],
            "cat_data": {
                "req:task:register": {
                    "received": 2
                },
                "reply:task:register": {
                    "replied": 2,
                    "ok": 2
                },
                "req:server_parent_listener:get_clients": {
                    "received": 2
                },
                "reply:server_parent_listener:get_clients": {
                    "replied": 2,
                    "ok": 2
                },
                "fwd.req:sm__STREAM:sm__DATA": {
                    "received": 56,
                    "forward": 56
                },
                "req:cellnet.channel:bye": {
                    "received": 2
                },
                "reply:cellnet.channel:bye": {
                    "replied": 2,
                    "ok": 2
                }
            }
        }
    },
    "received_msg_counters@server.simulate_job": {
        "type": "counter",
        "pool": {
            "name": "received_msg_counters@server.simulate_job",
            "description": "Result counters of received messages",
            "counter_names": [
                "received",
                "no_reply:none"
            ],
            "cat_data": {
                "req:sm__STREAM:sm__DATA": {
                    "received": 28,
                    "no_reply:none": 28
                }
            }
        }
    },
    "received_msg_counters@site-1": {
        "type": "counter",
        "pool": {
            "name": "received_msg_counters@site-1",
            "description": "Result counters of received messages",
            "counter_names": [
                "received"
            ],
            "cat_data": {
                "reply:task:register": {
                    "received": 1
                }
            }
        }
    },
    "received_msg_counters@site-2": {
        "type": "counter",
        "pool": {
            "name": "received_msg_counters@site-2",
            "description": "Result counters of received messages",
            "counter_names": [
                "received"
            ],
            "cat_data": {
                "reply:task:register": {
                    "received": 1
                }
            }
        }
    },
    "received_msg_sizes": {
        "type": "hist",
        "pool": {
            "name": "received_msg_sizes",
            "description": "Sizes of messages received (MBs)",
            "marks": [
                0.01,
                0.1,
                1,
                10,
                50,
                100,
                200,
                500,
                800,
                1000
            ],
            "unit": "MB",
            "cat_data": {
                "req:task:register": [
                    {
                        "count": 2,
                        "total": 3.814697265625e-06,
                        "min": 1.9073486328125e-06,
                        "max": 1.9073486328125e-06
                    },
                    "",
                    "",
                    "",
                    "",
                    "",
                    "",
                    "",
                    "",
                    "",
                    ""
                ],
                "req:server_parent_listener:get_clients": [
                    {
                        "count": 2,
                        "total": 1.9073486328125e-05,
                        "min": 9.5367431640625e-06,
                        "max": 9.5367431640625e-06
                    },
                    "",
                    "",
                    "",
                    "",
                    "",
                    "",
                    "",
                    "",
                    "",
                    ""
                ],
                "req:cellnet.channel:bye": [
                    {
                        "count": 2,
                        "total": 0.0,
                        "min": 0.0,
                        "max": 0.0
                    },
                    "",
                    "",
                    "",
                    "",
                    "",
                    "",
                    "",
                    "",
                    "",
                    ""
                ]
            }
        }
    },
    "received_msg_sizes@server.simulate_job": {
        "type": "hist",
        "pool": {
            "name": "received_msg_sizes@server.simulate_job",
            "description": "Sizes of messages received (MBs)",
            "marks": [
                0.01,
                0.1,
                1,
                10,
                50,
                100,
                200,
                500,
                800,
                1000
            ],
            "unit": "MB",
            "cat_data": {
                "req:sm__STREAM:sm__DATA": [
                    {
                        "count": 28,
                        "total": 0.025117874145507812,
                        "min": 0.00026702880859375,
                        "max": 0.0078582763671875
                    },
                    "",
                    "",
                    "",
                    "",
                    "",
                    "",
                    "",
                    "",
                    "",
                    ""
                ]
            }
        }
    },
    "received_msg_sizes@site-1": {
        "type": "hist",
        "pool": {
            "name": "received_msg_sizes@site-1",
            "description": "Sizes of messages received (MBs)",
            "marks": [
                0.01,
                0.1,
                1,
                10,
                50,
                100,
                200,
                500,
                800,
                1000
            ],
            "unit": "MB",
            "cat_data": {
                "reply:task:register": [
                    {
                        "count": 1,
                        "total": 0.0,
                        "min": 0.0,
                        "max": 0.0
                    },
                    "",
                    "",
                    "",
                    "",
                    "",
                    "",
                    "",
                    "",
                    "",
                    ""
                ]
            }
        }
    },
    "received_msg_sizes@site-2": {
        "type": "hist",
        "pool": {
            "name": "received_msg_sizes@site-2",
            "description": "Sizes of messages received (MBs)",
            "marks": [
                0.01,
                0.1,
                1,
                10,
                50,
                100,
                200,
                500,
                800,
                1000
            ],
            "unit": "MB",
            "cat_data": {
                "reply:task:register": [
                    {
                        "count": 1,
                        "total": 0.0,
                        "min": 0.0,
                        "max": 0.0
                    },
                    "",
                    "",
                    "",
                    "",
                    "",
                    "",
                    "",
                    "",
                    "",
                    ""
                ]
            }
        }
    },
    "received_stream_counters": {
        "type": "counter",
        "pool": {
            "name": "received_stream_counters",
            "description": "Counters of received streams",
            "counter_names": [
                "received"
            ],
            "cat_data": {}
        }
    },
    "received_stream_counters@server.simulate_job": {
        "type": "counter",
        "pool": {
            "name": "received_stream_counters@server.simulate_job",
            "description": "Counters of received streams",
            "counter_names": [
                "received"
            ],
            "cat_data": {
                "stream:aux_communication:__sync_runner__": {
                    "received": 2
                },
                "stream:server_command:get_task": {
                    "received": 18
                },
                "stream:aux_communication:__task_check__": {
                    "received": 4
                },
                "stream:server_command:submit_update": {
                    "received": 4
                }
            }
        }
    },
    "received_stream_counters@site-1": {
        "type": "counter",
        "pool": {
            "name": "received_stream_counters@site-1",
            "description": "Counters of received streams",
            "counter_names": [
                "received"
            ],
            "cat_data": {}
        }
    },
    "received_stream_counters@site-2": {
        "type": "counter",
        "pool": {
            "name": "received_stream_counters@site-2",
            "description": "Counters of received streams",
            "counter_names": [
                "received"
            ],
            "cat_data": {}
        }
    },
    "received_stream_sizes": {
        "type": "hist",
        "pool": {
            "name": "received_stream_sizes",
            "description": "Sizes of streams received (MBs)",
            "marks": [
                0.01,
                0.1,
                1,
                10,
                50,
                100,
                200,
                500,
                800,
                1000
            ],
            "unit": "MB",
            "cat_data": {}
        }
    },
    "received_stream_sizes@server.simulate_job": {
        "type": "hist",
        "pool": {
            "name": "received_stream_sizes@server.simulate_job",
            "description": "Sizes of streams received (MBs)",
            "marks": [
                0.01,
                0.1,
                1,
                10,
                50,
                100,
                200,
                500,
                800,
                1000
            ],
            "unit": "MB",
            "cat_data": {
                "stream:aux_communication:__sync_runner__": [
                    {
                        "count": 2,
                        "total": 0.0005340576171875,
                        "min": 0.00026702880859375,
                        "max": 0.00026702880859375
                    },
                    "",
                    "",
                    "",
                    "",
                    "",
                    "",
                    "",
                    "",
                    "",
                    ""
                ],
                "stream:server_command:get_task": [
                    {
                        "count": 18,
                        "total": 0.006557464599609375,
                        "min": 0.0003643035888671875,
                        "max": 0.0003643035888671875
                    },
                    "",
                    "",
                    "",
                    "",
                    "",
                    "",
                    "",
                    "",
                    "",
                    ""
                ],
                "stream:aux_communication:__task_check__": [
                    {
                        "count": 4,
                        "total": 0.001255035400390625,
                        "min": 0.00031375885009765625,
                        "max": 0.00031375885009765625
                    },
                    "",
                    "",
                    "",
                    "",
                    "",
                    "",
                    "",
                    "",
                    "",
                    ""
                ],
                "stream:server_command:submit_update": [
                    {
                        "count": 4,
                        "total": 0.016771316528320312,
                        "min": 0.0005273818969726562,
                        "max": 0.0078582763671875
                    },
                    "",
                    "",
                    "",
                    "",
                    "",
                    "",
                    "",
                    "",
                    "",
                    ""
                ]
            }
        }
    },
    "received_stream_sizes@site-1": {
        "type": "hist",
        "pool": {
            "name": "received_stream_sizes@site-1",
            "description": "Sizes of streams received (MBs)",
            "marks": [
                0.01,
                0.1,
                1,
                10,
                50,
                100,
                200,
                500,
                800,
                1000
            ],
            "unit": "MB",
            "cat_data": {}
        }
    },
    "received_stream_sizes@site-2": {
        "type": "hist",
        "pool": {
            "name": "received_stream_sizes@site-2",
            "description": "Sizes of streams received (MBs)",
            "marks": [
                0.01,
                0.1,
                1,
                10,
                50,
                100,
                200,
                500,
                800,
                1000
            ],
            "unit": "MB",
            "cat_data": {}
        }
    },
    "request_processing": {
        "type": "hist",
        "pool": {
            "name": "request_processing",
            "description": "Time spent (secs) by request processing callbacks (receiver)",
            "marks": [
                0.0001,
                0.0005,
                0.001,
                0.002,
                0.004,
                0.008,
                0.01,
                0.02,
                0.04,
                0.08,
                0.1,
                0.2,
                0.4,
                0.8,
                1.0,
                2.0
            ],
            "unit": "second",
            "cat_data": {
                "req:task:register": [
                    "",
                    {
                        "count": 2,
                        "total": 0.0003543399943737313,
                        "min": 0.00014969099720474333,
                        "max": 0.000204648997168988
                    },
                    "",
                    "",
                    "",
                    "",
                    "",
                    "",
                    "",
                    "",
                    "",
                    "",
                    "",
                    "",
                    "",
                    "",
                    ""
                ],
                "req:server_parent_listener:get_clients": [
                    {
                        "count": 1,
                        "total": 4.1248000343330204e-05,
                        "min": 4.1248000343330204e-05,
                        "max": 4.1248000343330204e-05
                    },
                    {
                        "count": 1,
                        "total": 0.0001395010040141642,
                        "min": 0.0001395010040141642,
                        "max": 0.0001395010040141642
                    },
                    "",
                    "",
                    "",
                    "",
                    "",
                    "",
                    "",
                    "",
                    "",
                    "",
                    "",
                    "",
                    "",
                    "",
                    ""
                ],
                "req:cellnet.channel:bye": [
                    {
                        "count": 2,
                        "total": 9.885701001621783e-05,
                        "min": 4.7537003410980105e-05,
                        "max": 5.132000660523772e-05
                    },
                    "",
                    "",
                    "",
                    "",
                    "",
                    "",
                    "",
                    "",
                    "",
                    "",
                    "",
                    "",
                    "",
                    "",
                    "",
                    ""
                ]
            }
        }
    },
    "request_processing@server.simulate_job": {
        "type": "hist",
        "pool": {
            "name": "request_processing@server.simulate_job",
            "description": "Time spent (secs) by request processing callbacks (receiver)",
            "marks": [
                0.0001,
                0.0005,
                0.001,
                0.002,
                0.004,
                0.008,
                0.01,
                0.02,
                0.04,
                0.08,
                0.1,
                0.2,
                0.4,
                0.8,
                1.0,
                2.0
            ],
            "unit": "second",
            "cat_data": {
                "req:sm__STREAM:sm__DATA": [
                    {
                        "count": 18,
                        "total": 0.001366022988804616,
                        "min": 5.892998888157308e-05,
                        "max": 9.577799937687814e-05
                    },
                    {
                        "count": 9,
                        "total": 0.0020854960021097213,
                        "min": 0.00011679100862238556,
                        "max": 0.0003645879914984107
                    },
                    {
                        "count": 1,
                        "total": 0.000782204995630309,
                        "min": 0.000782204995630309,
                        "max": 0.000782204995630309
                    },
                    "",
                    "",
                    "",
                    "",
                    "",
                    "",
                    "",
                    "",
                    "",
                    "",
                    "",
                    "",
                    "",
                    ""
                ]
            }
        }
    },
    "request_processing@site-1": {
        "type": "hist",
        "pool": {
            "name": "request_processing@site-1",
            "description": "Time spent (secs) by request processing callbacks (receiver)",
            "marks": [
                0.0001,
                0.0005,
                0.001,
                0.002,
                0.004,
                0.008,
                0.01,
                0.02,
                0.04,
                0.08,
                0.1,
                0.2,
                0.4,
                0.8,
                1.0,
                2.0
            ],
            "unit": "second",
            "cat_data": {}
        }
    },
    "request_processing@site-2": {
        "type": "hist",
        "pool": {
            "name": "request_processing@site-2",
            "description": "Time spent (secs) by request processing callbacks (receiver)",
            "marks": [
                0.0001,
                0.0005,
                0.001,
                0.002,
                0.004,
                0.008,
                0.01,
                0.02,
                0.04,
                0.08,
                0.1,
                0.2,
                0.4,
                0.8,
                1.0,
                2.0
            ],
            "unit": "second",
            "cat_data": {}
        }
    },
    "request_response": {
        "type": "hist",
        "pool": {
            "name": "request_response",
            "description": "Request/response time in secs (sender)",
            "marks": [
                0.0001,
                0.0005,
                0.001,
                0.002,
                0.004,
                0.008,
                0.01,
                0.02,
                0.04,
                0.08,
                0.1,
                0.2,
                0.4,
                0.8,
                1.0,
                2.0
            ],
            "unit": "second",
            "cat_data": {}
        }
    },
    "request_response@server.simulate_job": {
        "type": "hist",
        "pool": {
            "name": "request_response@server.simulate_job",
            "description": "Request/response time in secs (sender)",
            "marks": [
                0.0001,
                0.0005,
                0.001,
                0.002,
                0.004,
                0.008,
                0.01,
                0.02,
                0.04,
                0.08,
                0.1,
                0.2,
                0.4,
                0.8,
                1.0,
                2.0
            ],
            "unit": "second",
            "cat_data": {}
        }
    },
    "request_response@site-1": {
        "type": "hist",
        "pool": {
            "name": "request_response@site-1",
            "description": "Request/response time in secs (sender)",
            "marks": [
                0.0001,
                0.0005,
                0.001,
                0.002,
                0.004,
                0.008,
                0.01,
                0.02,
                0.04,
                0.08,
                0.1,
                0.2,
                0.4,
                0.8,
                1.0,
                2.0
            ],
            "unit": "second",
            "cat_data": {
                "reply:task:register": [
                    "",
                    "",
                    {
                        "count": 1,
                        "total": 0.0006089210510253906,
                        "min": 0.0006089210510253906,
                        "max": 0.0006089210510253906
                    },
                    "",
                    "",
                    "",
                    "",
                    "",
                    "",
                    "",
                    "",
                    "",
                    "",
                    "",
                    "",
                    "",
                    ""
                ]
            }
        }
    },
    "request_response@site-2": {
        "type": "hist",
        "pool": {
            "name": "request_response@site-2",
            "description": "Request/response time in secs (sender)",
            "marks": [
                0.0001,
                0.0005,
                0.001,
                0.002,
                0.004,
                0.008,
                0.01,
                0.02,
                0.04,
                0.08,
                0.1,
                0.2,
                0.4,
                0.8,
                1.0,
                2.0
            ],
            "unit": "second",
            "cat_data": {
                "reply:task:register": [
                    "",
                    {
                        "count": 1,
                        "total": 0.0004477500915527344,
                        "min": 0.0004477500915527344,
                        "max": 0.0004477500915527344
                    },
                    "",
                    "",
                    "",
                    "",
                    "",
                    "",
                    "",
                    "",
                    "",
                    "",
                    "",
                    "",
                    "",
                    "",
                    ""
                ]
            }
        }
    },
    "sent_msg_counters": {
        "type": "counter",
        "pool": {
            "name": "sent_msg_counters",
            "description": "Result counters of sent messages",
            "counter_names": [
                "sent",
                "forward"
            ],
            "cat_data": {
                "fwd.req:sm__STREAM:sm__DATA": {
                    "forward": 56
                }
            }
        }
    },
    "sent_msg_counters@server.simulate_job": {
        "type": "counter",
        "pool": {
            "name": "sent_msg_counters@server.simulate_job",
            "description": "Result counters of sent messages",
            "counter_names": [
                "sent"
            ],
            "cat_data": {
                "req:sm__STREAM:sm__DATA": {
                    "sent": 28
                }
            }
        }
    },
    "sent_msg_counters@site-1": {
        "type": "counter",
        "pool": {
            "name": "sent_msg_counters@site-1",
            "description": "Result counters of sent messages",
            "counter_names": [
                "sent",
                "ok"
            ],
            "cat_data": {
                "req:task:register": {
                    "sent": 1
                },
                "reply:task:register": {
                    "ok": 1
                }
            }
        }
    },
    "sent_msg_counters@site-2": {
        "type": "counter",
        "pool": {
            "name": "sent_msg_counters@site-2",
            "description": "Result counters of sent messages",
            "counter_names": [
                "sent",
                "ok"
            ],
            "cat_data": {
                "req:task:register": {
                    "sent": 1
                },
                "reply:task:register": {
                    "ok": 1
                }
            }
        }
    },
    "sent_msg_sizes": {
        "type": "hist",
        "pool": {
            "name": "sent_msg_sizes",
            "description": "Sizes of messages sent (MBs)",
            "marks": [
                0.01,
                0.1,
                1,
                10,
                50,
                100,
                200,
                500,
                800,
                1000
            ],
            "unit": "MB",
            "cat_data": {
                "reply:task:register": [
                    {
                        "count": 2,
                        "total": 0.0,
                        "min": 0.0,
                        "max": 0.0
                    },
                    "",
                    "",
                    "",
                    "",
                    "",
                    "",
                    "",
                    "",
                    "",
                    ""
                ],
                "reply:server_parent_listener:get_clients": [
                    {
                        "count": 2,
                        "total": 3.814697265625e-06,
                        "min": 1.9073486328125e-06,
                        "max": 1.9073486328125e-06
                    },
                    "",
                    "",
                    "",
                    "",
                    "",
                    "",
                    "",
                    "",
                    "",
                    ""
                ],
                "fwd.req:sm__STREAM:sm__DATA": [
                    {
                        "count": 56,
                        "total": 0.04775047302246094,
                        "min": 9.5367431640625e-06,
                        "max": 0.0078582763671875
                    },
                    "",
                    "",
                    "",
                    "",
                    "",
                    "",
                    "",
                    "",
                    "",
                    ""
                ],
                "reply:cellnet.channel:bye": [
                    {
                        "count": 2,
                        "total": 0.0,
                        "min": 0.0,
                        "max": 0.0
                    },
                    "",
                    "",
                    "",
                    "",
                    "",
                    "",
                    "",
                    "",
                    "",
                    ""
                ]
            }
        }
    },
    "sent_msg_sizes@server.simulate_job": {
        "type": "hist",
        "pool": {
            "name": "sent_msg_sizes@server.simulate_job",
            "description": "Sizes of messages sent (MBs)",
            "marks": [
                0.01,
                0.1,
                1,
                10,
                50,
                100,
                200,
                500,
                800,
                1000
            ],
            "unit": "MB",
            "cat_data": {
                "req:sm__STREAM:sm__DATA": [
                    {
                        "count": 28,
                        "total": 0.022632598876953125,
                        "min": 9.5367431640625e-06,
                        "max": 0.007846832275390625
                    },
                    "",
                    "",
                    "",
                    "",
                    "",
                    "",
                    "",
                    "",
                    "",
                    ""
                ]
            }
        }
    },
    "sent_msg_sizes@site-1": {
        "type": "hist",
        "pool": {
            "name": "sent_msg_sizes@site-1",
            "description": "Sizes of messages sent (MBs)",
            "marks": [
                0.01,
                0.1,
                1,
                10,
                50,
                100,
                200,
                500,
                800,
                1000
            ],
            "unit": "MB",
            "cat_data": {
                "req:task:register": [
                    {
                        "count": 1,
                        "total": 1.9073486328125e-06,
                        "min": 1.9073486328125e-06,
                        "max": 1.9073486328125e-06
                    },
                    "",
                    "",
                    "",
                    "",
                    "",
                    "",
                    "",
                    "",
                    "",
                    ""
                ]
            }
        }
    },
    "sent_msg_sizes@site-2": {
        "type": "hist",
        "pool": {
            "name": "sent_msg_sizes@site-2",
            "description": "Sizes of messages sent (MBs)",
            "marks": [
                0.01,
                0.1,
                1,
                10,
                50,
                100,
                200,
                500,
                800,
                1000
            ],
            "unit": "MB",
            "cat_data": {
                "req:task:register": [
                    {
                        "count": 1,
                        "total": 1.9073486328125e-06,
                        "min": 1.9073486328125e-06,
                        "max": 1.9073486328125e-06
                    },
                    "",
                    "",
                    "",
                    "",
                    "",
                    "",
                    "",
                    "",
                    "",
                    ""
                ]
            }
        }
    },
    "sent_stream_counters": {
        "type": "counter",
        "pool": {
            "name": "sent_stream_counters",
            "description": "Counters of sent streams",
            "counter_names": [
                "sent"
            ],
            "cat_data": {}
        }
    },
    "sent_stream_counters@server.simulate_job": {
        "type": "counter",
        "pool": {
            "name": "sent_stream_counters@server.simulate_job",
            "description": "Counters of sent streams",
            "counter_names": [
                "sent"
            ],
            "cat_data": {
                "blob:return_only:aux_communication:__sync_runner__": {
                    "sent": 2
                },
                "blob:return_only:server_command:get_task": {
                    "sent": 18
                },
                "blob:return_only:aux_communication:__task_check__": {
                    "sent": 4
                },
                "blob:return_only:server_command:submit_update": {
                    "sent": 4
                }
            }
        }
    },
    "sent_stream_counters@site-1": {
        "type": "counter",
        "pool": {
            "name": "sent_stream_counters@site-1",
            "description": "Counters of sent streams",
            "counter_names": [
                "sent"
            ],
            "cat_data": {}
        }
    },
    "sent_stream_counters@site-2": {
        "type": "counter",
        "pool": {
            "name": "sent_stream_counters@site-2",
            "description": "Counters of sent streams",
            "counter_names": [
                "sent"
            ],
            "cat_data": {}
        }
    },
    "sent_stream_sizes": {
        "type": "hist",
        "pool": {
            "name": "sent_stream_sizes",
            "description": "Sizes of streams sent (MBs)",
            "marks": [
                0.01,
                0.1,
                1,
                10,
                50,
                100,
                200,
                500,
                800,
                1000
            ],
            "unit": "MB",
            "cat_data": {}
        }
    },
    "sent_stream_sizes@server.simulate_job": {
        "type": "hist",
        "pool": {
            "name": "sent_stream_sizes@server.simulate_job",
            "description": "Sizes of streams sent (MBs)",
            "marks": [
                0.01,
                0.1,
                1,
                10,
                50,
                100,
                200,
                500,
                800,
                1000
            ],
            "unit": "MB",
            "cat_data": {
                "blob:return_only:aux_communication:__sync_runner__": [
                    {
                        "count": 2,
                        "total": 0.000499725341796875,
                        "min": 0.0002498626708984375,
                        "max": 0.0002498626708984375
                    },
                    "",
                    "",
                    "",
                    "",
                    "",
                    "",
                    "",
                    "",
                    "",
                    ""
                ],
                "blob:return_only:server_command:get_task": [
                    {
                        "count": 18,
                        "total": 0.02109527587890625,
                        "min": 0.000301361083984375,
                        "max": 0.007846832275390625
                    },
                    "",
                    "",
                    "",
                    "",
                    "",
                    "",
                    "",
                    "",
                    "",
                    ""
                ],
                "blob:return_only:aux_communication:__task_check__": [
                    {
                        "count": 4,
                        "total": 0.00099945068359375,
                        "min": 0.0002498626708984375,
                        "max": 0.0002498626708984375
                    },
                    "",
                    "",
                    "",
                    "",
                    "",
                    "",
                    "",
                    "",
                    "",
                    ""
                ],
                "blob:return_only:server_command:submit_update": [
                    {
                        "count": 4,
                        "total": 3.814697265625e-05,
                        "min": 9.5367431640625e-06,
                        "max": 9.5367431640625e-06
                    },
                    "",
                    "",
                    "",
                    "",
                    "",
                    "",
                    "",
                    "",
                    "",
                    ""
                ]
            }
        }
    },
    "sent_stream_sizes@site-1": {
        "type": "hist",
        "pool": {
            "name": "sent_stream_sizes@site-1",
            "description": "Sizes of streams sent (MBs)",
            "marks": [
                0.01,
                0.1,
                1,
                10,
                50,
                100,
                200,
                500,
                800,
                1000
            ],
            "unit": "MB",
            "cat_data": {}
        }
    },
    "sent_stream_sizes@site-2": {
        "type": "hist",
        "pool": {
            "name": "sent_stream_sizes@site-2",
            "description": "Sizes of streams sent (MBs)",
            "marks": [
                0.01,
                0.1,
                1,
                10,
                50,
                100,
                200,
                500,
                800,
                1000
            ],
            "unit": "MB",
            "cat_data": {}
        }
    },
    "sfm_send_frame": {
        "type": "hist",
        "pool": {
            "name": "sfm_send_frame",
            "description": "SFM send_frame time in secs",
            "marks": [
                0.0001,
                0.0005,
                0.001,
                0.002,
                0.004,
                0.008,
                0.01,
                0.02,
                0.04,
                0.08,
                0.1,
                0.2,
                0.4,
                0.8,
                1.0,
                2.0
            ],
            "unit": "second",
            "cat_data": {
                "TcpDriver": [
                    {
                        "count": 20,
                        "total": 0.0012258279894012958,
                        "min": 4.790400271303952e-05,
                        "max": 7.309399370569736e-05
                    },
                    {
                        "count": 11,
                        "total": 0.002938469988293946,
                        "min": 0.00013154400221537799,
                        "max": 0.00038352700357791036
                    },
                    "",
                    {
                        "count": 1,
                        "total": 0.0015698689967393875,
                        "min": 0.0015698689967393875,
                        "max": 0.0015698689967393875
                    },
                    "",
                    "",
                    "",
                    "",
                    "",
                    "",
                    "",
                    "",
                    "",
                    "",
                    "",
                    "",
                    ""
                ]
            }
        }
    }
}